pyqt_viewer_widget/__init__.py
pyqt_viewer_widget/viewerWidget.py
pyqt_viewer_widget-0.0.20.dist-info/LICENSE
pyqt_viewer_widget-0.0.20.dist-info/METADATA
pyqt_viewer_widget-0.0.20.dist-info/WHEEL
pyqt_viewer_widget-0.0.20.dist-info/top_level.txt
pyqt_viewer_widget-0.0.20.dist-info/RECORD
