Metadata-Version: 2.1
Name: pyqt-viewer-widget
Version: 0.0.20
Summary: PyQt viewer widget which helps you make viewer application easily
Home-page: https://github.com/yjg30737/pyqt-viewer-widget.git
Author: Jung Gyu Yoon
Author-email: yjg30737@gmail.com
License: MIT
Platform: UNKNOWN
License-File: LICENSE
Requires-Dist: PyQt5 (>=5.8)
Requires-Dist: pyqt-toast (>=0.0.1)
Requires-Dist: pyqt-single-image-graphics-view (>=0.0.1)
